EDMD_package/__init__.py
EDMD_package/__main__.py
EDMD_package/create_tables.py
EDMD_package/fit_dihedrals.py
EDMD_package/format_scores_csrosetta.py
EDMD_package/save_dihedrals.py
EDMD_package/visualize_dihedrals.py
EDMD_package/visualize_pef.py
edmd_package-2.0.6.dist-info/METADATA
edmd_package-2.0.6.dist-info/WHEEL
edmd_package-2.0.6.dist-info/licenses/LICENSE
edmd_package-2.0.6.dist-info/RECORD
