Metadata-Version: 2.4
Name: EDMD_package
Version: 2.0.6
Summary: This module can be used to analyse the Phi and Psi dihedral (or torsion) angle distribution in a protein structural ensemble (e.g., from Chemical-Shift-Rosetta), define potential energy functions (PEFs), and replace the original dihedral energy terms in GROMACS for molecular dynamics (MD) simulations.
Project-URL: Homepage, https://github.com/gadaneczm/EDMD_package
Author-email: Márton Gadanecz <marton.gadanecz@gmail.com>, Zsolt Fazekas <zsolt.fazekas.9@gmail.com>
License-Expression: MIT
License-File: LICENSE
Classifier: Operating System :: OS Independent
Classifier: Programming Language :: Python :: 3
Requires-Python: >=3.10
Requires-Dist: biopython~=1.81
Requires-Dist: matplotlib~=3.7.1
Requires-Dist: numpy~=1.26.4
